open_parny/__init__.py
open_parny/parny.py
open_parny-0.1.1.dist-info/METADATA
open_parny-0.1.1.dist-info/WHEEL
open_parny-0.1.1.dist-info/top_level.txt
open_parny-0.1.1.dist-info/RECORD
