Metadata-Version: 2.1
Name: open_parny
Version: 0.1.1
Summary: A Python package to send alerts to Parny.io webhooks.
Home-page: https://github.com/haday23/open-parny.git
Author: Hasan Aday
Author-email: hasan@parny.io
Classifier: Programming Language :: Python :: 3
Classifier: License :: OSI Approved :: MIT License
Classifier: Operating System :: OS Independent
Requires-Python: >=3.6
Requires-Dist: requests
